{
  "sections": {
    "16375654467d9d124d": {
      "type": "image-banner",
      "blocks": {
        "163756544668aa414f-0": {
          "type": "slide",
          "settings": {
            "large_image": "shopify:\/\/shop_images\/dgl17ayp2.jpg",
            "small_image": "shopify:\/\/shop_images\/dgl17ayp1_3840x_86a4740d-b872-4bee-9d95-71d93b1d3977.jpg",
            "heading": "New arrivals",
            "sub_heading": "Summer collection",
            "button_text": "Shop Now",
            "button_link": "shopify:\/\/collections"
          }
        },
        "5223dcdd-687e-434e-8011-08c95b9936bc": {
          "type": "slide",
          "settings": {
            "large_image": "shopify:\/\/shop_images\/84758nne2.jpg",
            "small_image": "shopify:\/\/shop_images\/84758nne1_3840x_6de55f19-8893-40e8-864a-eae443787f15.jpg",
            "heading": "Hot Trend",
            "sub_heading": "Spring Collection",
            "button_text": "Discover More",
            "button_link": "shopify:\/\/collections\/all"
          }
        },
        "a28fdaae-9b40-4547-be53-9deba9515d5e": {
          "type": "slide",
          "settings": {
            "large_image": "shopify:\/\/shop_images\/girl2_3840x_4f112ade-818b-4ad5-b9ad-4e27794a2e0d.jpg",
            "small_image": "shopify:\/\/shop_images\/girl1_3840x_99c9a37f-8f53-4b60-8808-325a2cc9e6eb.jpg",
            "heading": "Slideshow heading",
            "sub_heading": "Slideshow sub-heading",
            "button_text": "Button Text",
            "button_link": ""
          }
        }
      },
      "block_order": [
        "163756544668aa414f-0",
        "5223dcdd-687e-434e-8011-08c95b9936bc",
        "a28fdaae-9b40-4547-be53-9deba9515d5e"
      ],
      "settings": {
        "autoplay_banner_slides": true,
        "image_height": "md:h-screen-md",
        "image_overlay_opacity": 0,
        "heading_font_size": 8,
        "subheading_font_size": 4,
        "heading_color": "#000000",
        "subheading_color": "#000000",
        "button_text_color": "#000000",
        "heading_font_weight": 400,
        "subheading_font_weight": 400,
        "button_text_font_weight": 400,
        "banner_heading_font": "rubik_n4",
        "banner_subheading_font": "rubik_n4",
        "banner_button_font": "rubik_n4",
        "button_bg_color": "",
        "button_border_color": "#000000",
        "button_border_radius": "none",
        "banner_button_size": "2.4rem 3.6rem",
        "vertical_content_position": "center",
        "horizontal_content_position": "start"
      }
    },
    "1639992274f6a6c890": {
      "type": "collection-list-slider",
      "blocks": {
        "a6123582-2008-48a3-a090-8ae80b2bb3b2": {
          "type": "collection_list_slide",
          "settings": {
            "collection": "accessories"
          }
        },
        "b9334d54-6507-49ae-8e29-bb13714ce18e": {
          "type": "collection_list_slide",
          "settings": {
            "collection": "bags"
          }
        },
        "212ef2f3-5d0f-4d7d-92ce-a916fb01ab2a": {
          "type": "collection_list_slide",
          "settings": {
            "collection": "dresses"
          }
        },
        "8f0e5c56-37d5-466c-ae87-c693de5479c5": {
          "type": "collection_list_slide",
          "settings": {
            "collection": "hats"
          }
        },
        "a633d4a8-f14e-42f6-97f9-92c86c806038": {
          "type": "collection_list_slide",
          "settings": {
            "collection": "legwear"
          }
        },
        "5f2cb4a3-faa1-4c3c-b710-a0f37308ff2e": {
          "type": "collection_list_slide",
          "settings": {
            "collection": "sandals"
          }
        },
        "796df8dd-0665-4a12-9569-193b5f49a90e": {
          "type": "collection_list_slide",
          "settings": {
            "collection": "shirts"
          }
        },
        "220dbd58-85dc-40d0-a154-016e17628e9f": {
          "type": "collection_list_slide",
          "settings": {
            "collection": "shoes"
          }
        }
      },
      "block_order": [
        "a6123582-2008-48a3-a090-8ae80b2bb3b2",
        "b9334d54-6507-49ae-8e29-bb13714ce18e",
        "212ef2f3-5d0f-4d7d-92ce-a916fb01ab2a",
        "8f0e5c56-37d5-466c-ae87-c693de5479c5",
        "a633d4a8-f14e-42f6-97f9-92c86c806038",
        "5f2cb4a3-faa1-4c3c-b710-a0f37308ff2e",
        "796df8dd-0665-4a12-9569-193b5f49a90e",
        "220dbd58-85dc-40d0-a154-016e17628e9f"
      ],
      "settings": {
        "title": "Collections",
        "footer_font_size": 5,
        "center_footer_text": true,
        "show_arrow": true,
        "image_ratio": "portrait",
        "color_scheme": "none",
        "swipe_on_mobile": false,
        "image_padding": false,
        "show_view_all": false
      }
    },
    "1641296584966eafbb": {
      "type": "featured-collection",
      "blocks": {
        "164129658358d78757-0": {
          "type": "featured_collection",
          "settings": {
            "title": "Best seller",
            "collection": "all-products"
          }
        },
        "a1c20451-4844-40b6-9517-f5caf5e4cebe": {
          "type": "featured_collection",
          "settings": {
            "title": "Dresses",
            "collection": "dresses"
          }
        }
      },
      "block_order": [
        "164129658358d78757-0",
        "a1c20451-4844-40b6-9517-f5caf5e4cebe"
      ],
      "settings": {
        "show_view_all": true,
        "swipe_on_mobile": false,
        "products_to_show": 10,
        "products_per_row": 4,
        "image_ratio": "portrait",
        "show_secondary_image": true,
        "add_image_padding": false,
        "show_image_outline": false,
        "show_vendor": false,
        "show_rating": true
      }
    }
  },
  "order": [
    "16375654467d9d124d",
    "1639992274f6a6c890",
    "1641296584966eafbb"
  ]
}
